knowledge_exporter/__init__.py
knowledge_exporter/__version__.py
knowledge_exporter/exporter.py
knowledge_exporter/geektime.py
knowledge_exporter/knowledge.py
knowledge_exporter/provider.py
knowledge_exporter/utils.py
knowledge_exporter/bin/__init__.py
knowledge_exporter/bin/cpdf
knowledge_exporter/bin/cpdf.exe
knowledge_exporter-1.1.2.data/scripts/cpdf-wrapper
knowledge_exporter-1.1.2.dist-info/LICENSE
knowledge_exporter-1.1.2.dist-info/METADATA
knowledge_exporter-1.1.2.dist-info/WHEEL
knowledge_exporter-1.1.2.dist-info/entry_points.txt
knowledge_exporter-1.1.2.dist-info/top_level.txt
knowledge_exporter-1.1.2.dist-info/RECORD
