Metadata-Version: 2.1
Name: knowledge-exporter
Version: 1.1.2
Summary: Export content from knowledge plaform.
Home-page: https://github.com/kadaliao/knowledge-exporter
Author: Kada Liao
Author-email: kadaliao@gmail.com
License: UNKNOWN
Keywords: pdf,knowledge,download
Platform: UNKNOWN
Classifier: License :: OSI Approved :: MIT License
Classifier: Development Status :: 3 - Alpha
Classifier: Intended Audience :: Developers
Classifier: Operating System :: MacOS
Classifier: Operating System :: Microsoft :: Windows
Classifier: Programming Language :: Python :: 3 :: Only
Classifier: Programming Language :: Python :: 3.6
Classifier: Programming Language :: Python :: 3.7
Classifier: Programming Language :: Python :: 3.8
Requires-Python: >=3.6
Requires-Dist: pathvalidate (==2.3.0)
Requires-Dist: pyppeteer (==0.2.2)
Requires-Dist: tqdm (==4.49.0)
Requires-Dist: click (==7.1.2)
